notpages
