Metadata-Version: 1.0
Name: notpages
Version: 1.1.0
Summary: Pagination for discord.py embeds
Home-page: UNKNOWN
Author: UNKNOWN
Author-email: applebruto@gmail.com
License: UNKNOWN
Platform: UNKNOWN
